notifications_python_client/__init__.py
notifications_python_client/authentication.py
notifications_python_client/base.py
notifications_python_client/errors.py
notifications_python_client/notifications.py
notifications_python_client/py.typed
notifications_python_client/utils.py
notifications_python_client-10.0.1.dist-info/LICENSE
notifications_python_client-10.0.1.dist-info/METADATA
notifications_python_client-10.0.1.dist-info/WHEEL
notifications_python_client-10.0.1.dist-info/top_level.txt
notifications_python_client-10.0.1.dist-info/RECORD
